xaal/__init__.py
xaal/knx/__init__.py
xaal/knx/__main__.py
xaal/knx/bindings.py
xaal/knx/devices.py
xaal/knx/dpts.py
xaal/knx/gw.py
xaal/knx/knxrouter.py
xaal_knx-0.2.2.dist-info/METADATA
xaal_knx-0.2.2.dist-info/WHEEL
xaal_knx-0.2.2.dist-info/top_level.txt
xaal_knx-0.2.2.dist-info/RECORD
