Metadata-Version: 2.4
Name: xaal.knx
Version: 0.2.2
Summary: xAAL devices for KNX bus
Author-email: Jerome Kerdreux <Jerome.Kerdreux@imt-atlantique.fr>
License-Expression: GPL-3.0-or-later
Project-URL: Homepage, https://recherche.imt-atlantique.fr/xaal/
Project-URL: Documentation, https://gitlab.imt-atlantique.fr/xaal/code/python/-/blob/main/devices/protocols/KNX/README.rst
Project-URL: Source, https://gitlab.imt-atlantique.fr/xaal/code/python/-/tree/main/devices/protocols/KNX
Keywords: xaal,knx
Classifier: Programming Language :: Python
Classifier: Topic :: Home Automation
Requires-Dist: xaal.lib
Requires-Dist: xaal.schemas
Requires-Dist: gevent
